{
  "auth": {
    "latestangular40929ccc": {
      "service": "Cognito",
      "providerPlugin": "awscloudformation",
      "dependsOn": [],
      "customAuth": false,
      "frontendAuthConfig": {
        "socialProviders": [],
        "usernameAttributes": [],
        "signupAttributes": [
          "EMAIL"
        ],
        "passwordProtectionSettings": {
          "passwordPolicyMinLength": 8,
          "passwordPolicyCharacters": []
        },
        "mfaConfiguration": "OFF",
        "mfaTypes": [
          "SMS"
        ],
        "verificationMechanisms": [
          "EMAIL"
        ]
      }
    }
  },
  "api": {
    "latestangular": {
      "service": "AppSync",
      "providerPlugin": "awscloudformation",
      "output": {
        "authConfig": {
          "defaultAuthentication": {
            "authenticationType": "AMAZON_COGNITO_USER_POOLS",
            "userPoolConfig": {
              "userPoolId": "authlatestangular40929ccc"
            }
          },
          "additionalAuthenticationProviders": [
            {
              "authenticationType": "API_KEY",
              "apiKeyConfig": {
                "apiKeyExpirationDays": 7,
                "apiKeyExpirationDate": "2022-04-15T11:27:21.785Z",
                "description": "Additional auth type"
              }
            }
          ]
        }
      }
    },
    "AdminQueries": {
      "service": "API Gateway",
      "providerPlugin": "awscloudformation",
      "authorizationType": "AMAZON_COGNITO_USER_POOLS",
      "dependsOn": [
        {
          "category": "auth",
          "resourceName": "latestangular40929ccc",
          "attributes": [
            "UserPoolId"
          ]
        },
        {
          "category": "function",
          "resourceName": "AdminQueries3f5790d7",
          "attributes": [
            "Arn",
            "Name"
          ]
        }
      ]
    }
  },
  "function": {
    "AdminQueries3f5790d7": {
      "service": "Lambda",
      "providerPlugin": "awscloudformation",
      "build": true,
      "dependsOn": [
        {
          "category": "auth",
          "resourceName": "latestangular40929ccc",
          "attributes": [
            "UserPoolId"
          ]
        }
      ]
    }
  }
}